nested_mapping/__init__.py
nested_mapping/class_wrapper.py
nested_mapping/ipython.py
nested_mapping/nested_mapping.py
nested_mapping/nested_mapping_access.py
nested_mapping/typing.py
nested_mapping/visitor.py
nested_mapping/tools/__init__.py
nested_mapping/tools/filter.py
nested_mapping/tools/map.py
nested_mapping/tools/match.py
nested_mapping/tools/reorder_key.py
nested_mapping-0.11.dist-info/licenses/LICENSE
nested_mapping-0.11.dist-info/METADATA
nested_mapping-0.11.dist-info/WHEEL
nested_mapping-0.11.dist-info/top_level.txt
nested_mapping-0.11.dist-info/RECORD
